resy_mcp/__init__.py
resy_mcp/server.py
resy_mcp-0.1.0.dist-info/METADATA
resy_mcp-0.1.0.dist-info/WHEEL
resy_mcp-0.1.0.dist-info/entry_points.txt
resy_mcp-0.1.0.dist-info/licenses/LICENSE
resy_mcp-0.1.0.dist-info/RECORD
